spark_price_transparency/__init__.py
spark_price_transparency/curate_viz.py
spark_price_transparency/end2end_job_viz.py
spark_price_transparency/end2end_viz.py
spark_price_transparency/entity_viz.py
spark_price_transparency/guide.py
spark_price_transparency/in_network.py
spark_price_transparency/methods_viz.py
spark_price_transparency/pt_analytic_table.py
spark_price_transparency/pt_files.py
spark_price_transparency/pt_functions.py
spark_price_transparency/pt_ingest_table.py
spark_price_transparency/pt_raw.py
spark_price_transparency/pt_schema.py
spark_price_transparency/pt_stage.py
spark_price_transparency/pt_table.py
spark_price_transparency/pt_types.py
spark_price_transparency/table.py
spark_price_transparency/table_analytic.py
spark_price_transparency/table_stream_tgt.py
spark_price_transparency/unified_viz.py
spark_price_transparency/allowed_amounts/__init__.py
spark_price_transparency/allowed_amounts/aa_header.py
spark_price_transparency/allowed_amounts/aa_network.py
spark_price_transparency/allowed_amounts/curate_viz.py
spark_price_transparency/allowed_amounts/files.py
spark_price_transparency/allowed_amounts/out_amount.py
spark_price_transparency/allowed_amounts/out_code.py
spark_price_transparency/allowed_amounts/schema.py
spark_price_transparency/in_network/__init__.py
spark_price_transparency/in_network/inr_header.py
spark_price_transparency/in_network/inr_network.py
spark_price_transparency/in_network/inr_provider.py
spark_price_transparency/in_network_rates/__init__.py
spark_price_transparency/in_network_rates/curate_viz.py
spark_price_transparency/in_network_rates/files.py
spark_price_transparency/in_network_rates/in_coverage.py
spark_price_transparency/in_network_rates/in_pr_loc.py
spark_price_transparency/in_network_rates/in_provider.py
spark_price_transparency/in_network_rates/in_rate.py
spark_price_transparency/in_network_rates/inr_header.py
spark_price_transparency/in_network_rates/inr_network.py
spark_price_transparency-0.1.89.dist-info/METADATA
spark_price_transparency-0.1.89.dist-info/WHEEL
spark_price_transparency-0.1.89.dist-info/top_level.txt
spark_price_transparency-0.1.89.dist-info/zip-safe
spark_price_transparency-0.1.89.dist-info/RECORD
