Metadata-Version: 2.1
Name: spark-price-transparency
Version: 0.1.89
Summary: Price Transparency for Spark
Home-page: UNKNOWN
Author: Brad Barker
Author-email: brad@ratiocinate.com
License: Databricks Labs
Keywords: CMS Gov Price Transparency Guideline Prescription In-Network table-of-contents provider-reference in-network-rates allowed-amounts
Platform: UNKNOWN
Classifier: Programming Language :: Python :: 3.8
Classifier: Topic :: System :: Distributed Computing
Classifier: Topic :: Database :: Database Engines/Servers
